potara/__init__.py
potara/document.py
potara/similaritymeasures.py
potara/summarizer.py
potara/takahe.py
tests/__init__.py
tests/test_all.py
potara-1.0.2.dist-info/LICENSE
potara-1.0.2.dist-info/METADATA
potara-1.0.2.dist-info/WHEEL
potara-1.0.2.dist-info/top_level.txt
potara-1.0.2.dist-info/RECORD
