Metadata-Version: 2.1
Name: potara
Version: 1.0.2
Summary: A multi-document summarizer based on ILP and sentence fusion.
Home-page: https://github.com/sildar/potara
Author: Remi Bois
Author-email: remibois.contact@gmail.com
License: Apache
Keywords: summarization
Platform: UNKNOWN
Classifier: Programming Language :: Python :: 3
Classifier: Programming Language :: Python :: 3.5
Classifier: Programming Language :: Python :: 3.6
Classifier: Development Status :: 5 - Production/Stable
Classifier: License :: OSI Approved :: MIT License
Classifier: Topic :: Scientific/Engineering :: Information Analysis
Classifier: Topic :: Text Processing :: Linguistic
Requires-Dist: gensim (==3.6.0)
Requires-Dist: networkx (==1.8.1)
Requires-Dist: nltk (==3.4.5)
Requires-Dist: pulp
Requires-Dist: setuptools (==40.6.3)
Requires-Dist: python-coveralls (==2.4.2)
Requires-Dist: six (==1.12.0)
Requires-Dist: requests (>=2.21.0)
